jj/__init__.py
jj/__main__.py
jj/_core.py
jj/_entry_point.py
jj/_load_module.py
jj/_version.py
jj/py.typed
jj/apps/__init__.py
jj/apps/_abstract_app.py
jj/apps/_base_app.py
jj/apps/_default_app.py
jj/expiration_policy/__init__.py
jj/expiration_policy/_expiration_policy.py
jj/expiration_policy/_expire_after_requests.py
jj/expiration_policy/_expire_never.py
jj/handlers/__init__.py
jj/handlers/_handler.py
jj/handlers/_handler_function.py
jj/http/__init__.py
jj/http/codes/__init__.py
jj/http/headers/__init__.py
jj/http/methods/__init__.py
jj/logs/__init__.py
jj/logs/_filter.py
jj/logs/_logger.py
jj/logs/_request_filter.py
jj/logs/_system_log_filter.py
jj/logs/formatters/__init__.py
jj/logs/formatters/_formatter.py
jj/logs/formatters/_simple_formatter.py
jj/logs/formatters/_template_formatter.py
jj/matchers/__init__.py
jj/matchers/_resolvable_matcher.py
jj/matchers/attribute_matchers/__init__.py
jj/matchers/attribute_matchers/_attribute_matcher.py
jj/matchers/attribute_matchers/_contain_matcher.py
jj/matchers/attribute_matchers/_equal_matcher.py
jj/matchers/attribute_matchers/_exist_matcher.py
jj/matchers/attribute_matchers/_multi_dict_matcher.py
jj/matchers/attribute_matchers/_regex_matcher.py
jj/matchers/attribute_matchers/_route_matcher.py
jj/matchers/logical_matchers/__init__.py
jj/matchers/logical_matchers/_all_matcher.py
jj/matchers/logical_matchers/_any_matcher.py
jj/matchers/logical_matchers/_logical_matcher.py
jj/matchers/request_matchers/__init__.py
jj/matchers/request_matchers/_header_matcher.py
jj/matchers/request_matchers/_method_matcher.py
jj/matchers/request_matchers/_param_matcher.py
jj/matchers/request_matchers/_path_matcher.py
jj/matchers/request_matchers/_request_matcher.py
jj/middlewares/__init__.py
jj/middlewares/_abstract_middleware.py
jj/middlewares/_base_middleware.py
jj/middlewares/_logger_middleware.py
jj/middlewares/_middleware_type.py
jj/middlewares/_root_middleware.py
jj/middlewares/_self_middleware.py
jj/mock/__init__.py
jj-2.13.1.dist-info/licenses/LICENSE.txt
jj-2.13.1.dist-info/METADATA
jj-2.13.1.dist-info/WHEEL
jj-2.13.1.dist-info/entry_points.txt
jj-2.13.1.dist-info/top_level.txt
jj-2.13.1.dist-info/RECORD
