Metadata-Version: 2.4
Name: jj
Version: 2.13.1
Summary: Remote HTTP Mock
Home-page: https://github.com/jj-mock/jj
Author: Nikita Tsvetkov
Author-email: tsv1@fastmail.com
License: Apache-2.0
Project-URL: Docs, https://jj-mock.io
Project-URL: GitHub, https://github.com/jj-mock/jj
Classifier: License :: OSI Approved :: Apache Software License
Classifier: Programming Language :: Python :: 3.9
Classifier: Programming Language :: Python :: 3.10
Classifier: Programming Language :: Python :: 3.11
Classifier: Programming Language :: Python :: 3.12
Classifier: Programming Language :: Python :: 3.13
Classifier: Typing :: Typed
Requires-Python: >=3.8
License-File: LICENSE.txt
Requires-Dist: aiohttp<4.0,>=3.5
Requires-Dist: multidict<7.0,>=4.5
Requires-Dist: packed<1.0,>=0.1
Requires-Dist: rtry<2.0,>=1.3
Requires-Dist: undecorated<0.4,>=0.3
Dynamic: author
Dynamic: author-email
Dynamic: classifier
Dynamic: description
Dynamic: description-content-type
Dynamic: home-page
Dynamic: license
Dynamic: license-file
Dynamic: project-url
Dynamic: requires-dist
Dynamic: requires-python
Dynamic: summary
